empowernow_common/__init__.py
empowernow_common/arn.py
empowernow_common/errors.py
empowernow_common/exceptions.py
empowernow_common/identity.py
empowernow_common/kafka_audit.py
empowernow_common/py.typed
empowernow_common/settings.py
empowernow_common/authzen/__init__.py
empowernow_common/authzen/client.py
empowernow_common/authzen/models.py
empowernow_common/authzen/secure_client.py
empowernow_common/cache/__init__.py
empowernow_common/cache/redis_backend.py
empowernow_common/client/__init__.py
empowernow_common/examples/__init__.py
empowernow_common/examples/fastapi_demo.py
empowernow_common/fastapi/__init__.py
empowernow_common/fips/__init__.py
empowernow_common/fips/algorithms.py
empowernow_common/fips/entropy.py
empowernow_common/fips/validator.py
empowernow_common/jwt/__init__.py
empowernow_common/jwt/config.py
empowernow_common/jwt/errors.py
empowernow_common/jwt/factory.py
empowernow_common/jwt/lightweight_validator.py
empowernow_common/jwt/utils.py
empowernow_common/jwt/validators.py
empowernow_common/kafka/platform_producer.py
empowernow_common/kafka/topics.py
empowernow_common/oauth/__init__.py
empowernow_common/oauth/ciba.py
empowernow_common/oauth/claims.py
empowernow_common/oauth/client.py
empowernow_common/oauth/dpop.py
empowernow_common/oauth/jar.py
empowernow_common/oauth/jarm.py
empowernow_common/oauth/network.py
empowernow_common/oauth/par.py
empowernow_common/oauth/pdp_integration_modes.py
empowernow_common/oauth/rar.py
empowernow_common/oauth/security.py
empowernow_common/oauth/smart_oauth_client.py
empowernow_common/oauth/sync.py
empowernow_common/redis/__init__.py
empowernow_common/redis/enterprise_redis_service.py
empowernow_common/rfc/__init__.py
empowernow_common/rfc/ciba.py
empowernow_common/rfc/jarm.py
empowernow_common/secret_loader/__init__.py
empowernow_common/secret_loader/providers.py
empowernow_common/utils/__init__.py
empowernow_common/utils/env.py
empowernow_common/utils/logging_config.py
empowernow_common/utils/metrics.py
empowernow_sdk-2.3.18.dist-info/licenses/LICENSE
empowernow_sdk-2.3.18.dist-info/METADATA
empowernow_sdk-2.3.18.dist-info/WHEEL
empowernow_sdk-2.3.18.dist-info/top_level.txt
empowernow_sdk-2.3.18.dist-info/RECORD
