Metadata-Version: 2.4
Name: empowernow-sdk
Version: 2.3.18
Summary: Comprehensive OAuth 2.1 / FAPI + AuthZEN PDP + FIPS client library
Author-email: EmpowerNow Security Team <security@empowernow.dev>
License: Apache-2.0
Project-URL: Homepage, https://github.com/EmpowerNowAI/python-sdk
Project-URL: Repository, https://github.com/EmpowerNowAI/python-sdk
Project-URL: Issues, https://github.com/EmpowerNowAI/python-sdk/issues
Classifier: Programming Language :: Python :: 3
Classifier: License :: OSI Approved :: Apache Software License
Classifier: Operating System :: OS Independent
Classifier: Development Status :: 4 - Beta
Classifier: Topic :: Security :: Cryptography
Requires-Python: >=3.10
License-File: LICENSE
Requires-Dist: cryptography>=41.0.0
Requires-Dist: httpx>=0.25.0
Requires-Dist: python-jose[cryptography]>=3.3.0
Requires-Dist: prometheus_client>=0.17.1
Provides-Extra: dev
Requires-Dist: pytest>=7.0.0; extra == "dev"
Requires-Dist: pytest-asyncio>=0.21.0; extra == "dev"
Requires-Dist: pytest-cov>=4.0.0; extra == "dev"
Requires-Dist: pyjwt>=2.8; extra == "dev"
Requires-Dist: trio>=0.25; extra == "dev"
Requires-Dist: black>=23.0.0; extra == "dev"
Requires-Dist: isort>=5.0.0; extra == "dev"
Requires-Dist: mypy>=1.0.0; extra == "dev"
Requires-Dist: flake8>=6.0.0; extra == "dev"
Requires-Dist: pre-commit>=3.0.0; extra == "dev"
Requires-Dist: respx>=0.20.0; extra == "dev"
Dynamic: license-file
